{
  "event_id": "2025-11-07-topic-180ee790",
  "date": "2025-11-07",
  "title": "特朗普官宣降价减肥药企高管当场晕倒",
  "category": "健康政策与公共服务",
  "health_minor": "医疗保障政策",
  "sentiment": -0.4,
  "sentiment_vector": [
    {
      "name": "喜悦",
      "value": 0.05
    },
    {
      "name": "信任",
      "value": 0.05
    },
    {
      "name": "恐惧",
      "value": 0.15
    },
    {
      "name": "惊喜",
      "value": 0.25
    },
    {
      "name": "伤心",
      "value": 0.2
    },
    {
      "name": "讨厌",
      "value": 0.3
    },
    {
      "name": "气愤",
      "value": 0.4
    },
    {
      "name": "期盼",
      "value": 0.05
    }
  ],
  "region": "国外",
  "start_ts": 1762498800,
  "end_ts": 1762502400,
  "heat_peak": 516354.0,
  "point_count": 2,
  "points": [
    {
      "ts": 1762498800,
      "heat": 516354.0,
      "rank": null
    },
    {
      "ts": 1762502400,
      "heat": 516354.0,
      "rank": null
    }
  ],
  "summary": "当地时间11月6日，美国总统特朗普官宣，与制药巨头礼来、诺和诺德达成药品控价协议，降低GLP-1类肥胖药物的价格，在礼来公司首席执行官发言时，诺和诺德公司的高管突然晕倒，在众人搀扶下躺在总统办公室的地板上。",
  "tags": [
    "特朗普官宣降价减肥药企高管当场晕倒",
    "海外新鲜事",
    "热点现场",
    "特朗普直播时医药代表突然晕倒",
    "美官员称明年美国人平均减重360斤",
    "特朗普对晕倒官员旁若无物"
  ],
  "tag_graph": {
    "nodes": [
      {
        "id": "特朗普官宣降价减肥药企高管当场晕倒",
        "label": "特朗普官宣降价减肥药企高管当场晕倒",
        "weight": 1.0,
        "community": null
      },
      {
        "id": "海外新鲜事",
        "label": "海外新鲜事",
        "weight": 1.0,
        "community": null
      },
      {
        "id": "热点现场",
        "label": "热点现场",
        "weight": 1.0,
        "community": null
      },
      {
        "id": "特朗普直播时医药代表突然晕倒",
        "label": "特朗普直播时医药代表突然晕倒",
        "weight": 1.0,
        "community": null
      },
      {
        "id": "美官员称明年美国人平均减重360斤",
        "label": "美官员称明年美国人平均减重360斤",
        "weight": 1.0,
        "community": null
      },
      {
        "id": "特朗普对晕倒官员旁若无物",
        "label": "特朗普对晕倒官员旁若无物",
        "weight": 1.0,
        "community": null
      }
    ],
    "edges": []
  },
  "wordcloud": [],
  "emotions": [
    {
      "name": "喜悦",
      "value": 0.05
    },
    {
      "name": "信任",
      "value": 0.05
    },
    {
      "name": "恐惧",
      "value": 0.15
    },
    {
      "name": "惊喜",
      "value": 0.25
    },
    {
      "name": "伤心",
      "value": 0.2
    },
    {
      "name": "讨厌",
      "value": 0.3
    },
    {
      "name": "气愤",
      "value": 0.4
    },
    {
      "name": "期盼",
      "value": 0.05
    }
  ],
  "sample_posts": []
}
